fets/__init__.py
fets/counter.py
fets/date.py
fets/math.py
fets/pipeline.py
fets/selection.py
fets/text.py
fets-0.5.3.dist-info/METADATA
fets-0.5.3.dist-info/RECORD
fets-0.5.3.dist-info/WHEEL
fets-0.5.3.dist-info/top_level.txt
