Metadata-Version: 2.1
Name: fets
Version: 0.5.3
Summary: Feature Engineering Transformer Set
Home-page: https://gitlab.com/redsharpbyte/fets
Author: Red Boumghar
License: BSD
Keywords: data,feature-engineering,feature-extraction,machine-learning,transformer,transformation,pipeline
Platform: UNKNOWN
Classifier: Development Status :: 3 - Alpha
Classifier: Intended Audience :: Developers
Classifier: Programming Language :: Python :: 3
Classifier: License :: OSI Approved :: BSD License
Requires-Python: >=3
Provides-Extra: test
Requires-Dist: numpy
Requires-Dist: scipy
Requires-Dist: pandas
Requires-Dist: scikit-learn
Requires-Dist: joblib
Provides-Extra: test
Requires-Dist: pytest; extra == 'test'
